webint_cache/__init__.py
webint_cache/silos.py
webint_cache/templates/__init__.py
webint_cache/templates/crawl_enqueued.html
webint_cache/templates/index.html
webint_cache/templates/site.html
webint_cache/templates/sites.html
webint_cache-0.0.12.dist-info/METADATA
webint_cache-0.0.12.dist-info/entry_points.txt
webint_cache-0.0.12.dist-info/WHEEL
webint_cache-0.0.12.dist-info/RECORD
